[{"id":"yI5eFscl5Ds","title":"Unstoppable TOP Player Team in Summoners War","thumbnails":"https:\/\/i.ytimg.com\/vi\/yI5eFscl5Ds\/mqdefault.jpg","name":"SWBattle","date":"2020-07-02T12:11:46Z"},{"id":"Nr1B3uI6yAU","title":"Double GARUDAs Cleave Team in Summoners War","thumbnails":"https:\/\/i.ytimg.com\/vi\/Nr1B3uI6yAU\/mqdefault.jpg","name":"SWBattle","date":"2020-07-02T03:00:06Z"},{"id":"DlzDYbvbCYI","title":"MASS Twins Power in RTA! - Summoners War","thumbnails":"https:\/\/i.ytimg.com\/vi\/DlzDYbvbCYI\/mqdefault.jpg","name":"Kenji SW","date":"2020-07-02T00:15:00Z"},{"id":"sLPrZ4rFpHw","title":"Malite Wants To Be Hit - Summoners War","thumbnails":"https:\/\/i.ytimg.com\/vi\/sLPrZ4rFpHw\/mqdefault.jpg","name":"SonX2","date":"2020-07-02T00:00:09Z"},{"id":"eOSaO6v5BiU","title":"PERFECT FEI (One Shot) Performance - Summoners War","thumbnails":"https:\/\/i.ytimg.com\/vi\/eOSaO6v5BiU\/mqdefault.jpg","name":"Kenji SW","date":"2020-07-01T16:07:36Z"},{"id":"GkzPndkph5A","title":"YOLO Team with Pang, Tyron, Raoq and Tarq - Summoners War","thumbnails":"https:\/\/i.ytimg.com\/vi\/GkzPndkph5A\/mqdefault.jpg","name":"SWBattle","date":"2020-07-01T12:05:02Z"},{"id":"jXVlL57boec","title":"Hungry Dog ft. Angry Cat - Summoners War","thumbnails":"https:\/\/i.ytimg.com\/vi\/jXVlL57boec\/mqdefault.jpg","name":"Good Soup SW","date":"2020-07-01T10:35:44Z"},{"id":"MPSw3lVS8aY","title":"TOMATO goes Crazy in Special League! - Summoners War","thumbnails":"https:\/\/i.ytimg.com\/vi\/MPSw3lVS8aY\/mqdefault.jpg","name":"Kenji SW","date":"2020-07-01T10:19:22Z"},{"id":"Txc3orB-LB8","title":"Buffed Light Gargoyle Phenaka - Summoners War","thumbnails":"https:\/\/i.ytimg.com\/vi\/Txc3orB-LB8\/mqdefault.jpg","name":"SonX2","date":"2020-07-01T09:00:08Z"},{"id":"p7q9mUAB7-E","title":"First Pick 300+ SPD Kroa - Summoners War","thumbnails":"https:\/\/i.ytimg.com\/vi\/p7q9mUAB7-E\/mqdefault.jpg","name":"SWBattle","date":"2020-07-01T03:09:41Z"},{"id":"VpwoBZmaoHM","title":"Faintmem Will Crush Your Hopes With Cichlid - Summoners War","thumbnails":"https:\/\/i.ytimg.com\/vi\/VpwoBZmaoHM\/mqdefault.jpg","name":"SonX2","date":"2020-07-01T00:00:06Z"},{"id":"Us5TxZCLcoo","title":"Blueshen X Shumar Brutality in RTA! - Summoners War","thumbnails":"https:\/\/i.ytimg.com\/vi\/Us5TxZCLcoo\/mqdefault.jpg","name":"Kenji SW","date":"2020-06-30T12:42:40Z"},{"id":"7DCuB4eWX_I","title":"Buffed Light Magical Archer Chris - Summoners War","thumbnails":"https:\/\/i.ytimg.com\/vi\/7DCuB4eWX_I\/mqdefault.jpg","name":"SonX2","date":"2020-06-30T12:00:03Z"},{"id":"vdd0mZZ83HM","title":"The Rise Of Sian (Water Joker) in 4* Special League - Summoners War","thumbnails":"https:\/\/i.ytimg.com\/vi\/vdd0mZZ83HM\/mqdefault.jpg","name":"Good Soup SW","date":"2020-06-30T10:08:45Z"},{"id":"z1OyHovuRmY","title":"Mookwol | The Dark Art Master in RTA - Summoners War","thumbnails":"https:\/\/i.ytimg.com\/vi\/z1OyHovuRmY\/mqdefault.jpg","name":"Good Soup SW","date":"2020-05-30T17:22:27Z"},{"id":"nW4a6I5XE9s","title":"Jeogun | The Fire Art Master in RTA - Summoners War","thumbnails":"https:\/\/i.ytimg.com\/vi\/nW4a6I5XE9s\/mqdefault.jpg","name":"Good Soup SW","date":"2020-05-28T09:35:58Z"}]